langchain_qwen3/__init__.py
langchain_qwen3/embeddings.py
langchain_qwen3/py.typed
langchain_qwen3-0.1.2.dist-info/METADATA
langchain_qwen3-0.1.2.dist-info/WHEEL
langchain_qwen3-0.1.2.dist-info/licenses/LICENSE
langchain_qwen3-0.1.2.dist-info/RECORD
